ha7000d/__init__.py
ha7000d/common.py
ha7000d/ha7062d.py
ha7000d/version.py
ha7000d-0.1.5.dist-info/LICENSE
ha7000d-0.1.5.dist-info/METADATA
ha7000d-0.1.5.dist-info/WHEEL
ha7000d-0.1.5.dist-info/top_level.txt
ha7000d-0.1.5.dist-info/RECORD
