Metadata-Version: 2.1
Name: ha7000d
Version: 0.1.5
Summary: Python interface to Holzworth HA7062D Phase Noise Analyzer
Home-page: https://github.com/l-johnston/ha7000d
Author: Lee Johnston
Author-email: lee.johnston.100@gmail.com
License: MIT
Platform: UNKNOWN
Classifier: Programming Language :: Python :: 3
Classifier: Topic :: Scientific/Engineering
Classifier: License :: OSI Approved :: MIT License
Classifier: Intended Audience :: Science/Research
Requires-Dist: unyt
